{
  "schemaVersion": "1.0",
  "epic": "golden-path-autonomous-delivery",
  "status": "phase5_complete",
  "factoryQueueId": "factory-milestone-c-mrf5x73y",
  "githubIssueUrl": null,
  "engineeringTeam": {
    "projectId": "PRJ-7494D1BC",
    "taskId": "TSK-017",
    "projectName": "Factory delivery — Milestone C agent autonomy verify [factory-milestone-c-mrf5x73y]",
    "requirements": "Prove GP-003/004/014/017/019/020-021/023 agent-driven factory delivery on coordinated stack.",
    "templateTier": "Simple",
    "changeKind": null,
    "changedFiles": [],
    "contractVersion": 1,
    "contractValidationStatus": "valid",
    "approvalMode": "policy",
    "forgeDispatch": {
      "targetRepo": "wiinc1/engineering-team",
      "projectId": "engineering-team",
      "domain": "workflow",
      "affectsUi": false
    },
    "forgeExecutionReadiness": null
  },
  "change": {
    "kind": null,
    "changedFiles": []
  },
  "forgeadapter": {
    "taskId": "TSK-GOLDENF5X73Y",
    "startJobId": null,
    "completeJobId": null,
    "forgeAuditDir": "/Users/wiinc2/.grok/worktrees/workspace-engineering-team/strategy-review/observability/milestone-c-staging-live/factory-delivery/stack/factory-milestone-c-mrf5x73y/forge-seed",
    "runtimeExecutionState": "skipped_forge_seed"
  },
  "stepsCompleted": [
    "GP-002",
    "GP-003",
    "GP-004",
    "GP-005",
    "GP-006",
    "GP-007",
    "GP-008",
    "GP-009",
    "GP-010",
    "GP-011",
    "GP-012",
    "GP-013",
    "GP-014",
    "GP-015",
    "GP-016",
    "GP-017",
    "GP-018",
    "GP-019",
    "GP-020",
    "GP-021",
    "GP-026"
  ],
  "startedAt": "2026-07-10T16:41:12.777Z",
  "completedAt": null,
  "phase0": {
    "mode": "factory_intake",
    "baseUrl": "http://127.0.0.1:13000",
    "tenantId": "engineering-team",
    "actorId": "factory-orchestrator",
    "persistDir": "/Users/wiinc2/.grok/worktrees/workspace-engineering-team/strategy-review/observability/milestone-c-staging-live/factory-delivery/stack/factory-milestone-c-mrf5x73y"
  },
  "phase1": {
    "completedAt": "2026-07-10T16:41:24.488Z",
    "baseUrl": "http://127.0.0.1:13000",
    "tenantId": "engineering-team",
    "actorId": "factory-orchestrator",
    "persistDir": null,
    "bootstrappedPhase0": false,
    "projectionRuns": [
      {
        "label": "pre-contract-record",
        "skipped": true,
        "reason": "worker_caught_up_after_wait",
        "mode": "always_on_worker",
        "projectionLagSeconds": 0,
        "processed": 0,
        "failed": 0,
        "retries": 0
      },
      {
        "label": "execution-contract-recorded",
        "skipped": true,
        "reason": "worker_caught_up_after_wait",
        "mode": "always_on_worker",
        "projectionLagSeconds": 0,
        "processed": 0,
        "failed": 0,
        "retries": 0
      },
      {
        "label": "execution-contract-approved",
        "skipped": true,
        "reason": "worker_caught_up_after_wait",
        "mode": "always_on_worker",
        "projectionLagSeconds": 0,
        "processed": 0,
        "failed": 0,
        "retries": 0
      }
    ],
    "api": {
      "pmRefinementMode": "refinement_start",
      "pmRefinementStatus": 202,
      "pmRefinementContractVersion": null,
      "pmRefinementDelegated": false,
      "pmRefinementSessionId": null,
      "architectHandoffMode": "embedded_in_execution_contract",
      "architectDelegated": false,
      "architectSessionId": null,
      "architectHandoffStatus": 200,
      "recordContractStatus": 201,
      "approveContractStatus": 201,
      "forgeReadinessStatus": 422,
      "taskDetailBeforeStatus": 200,
      "taskDetailAfterStatus": 200
    },
    "contract": {
      "version": 1,
      "templateTier": "Simple",
      "factoryTemplateTier": "Simple",
      "validationStatus": "valid",
      "autoApprovalPolicy": {
        "policy_version": "execution-contract-low-risk-simple-auto-approval.v1",
        "status": "ready",
        "canAutoApprove": true,
        "operatorApprovalRequired": false,
        "rationale": "Low-risk Simple Execution Contract meets all policy criteria: complete acceptance criteria, no risk flags, no unresolved dependencies, no production auth/security/data-model paths, and a clear rollback path.",
        "criteria": {
          "templateTier": "Simple",
          "riskFlags": [],
          "acceptanceCriteriaComplete": true,
          "acceptanceCriteriaCount": 1,
          "unresolvedDependencies": [],
          "productionSensitivePaths": [],
          "rollbackPathClear": true,
          "rollbackPath": "Rollback by reverting the pilot PR and removing the README golden-path marker.",
          "reviewerApprovalReady": true
        },
        "blockingReasons": [],
        "metricsPolicy": {
          "measuredBy": [
            "feature_operator_trusted_autonomous_delivery_rate",
            "feature_execution_contract_auto_approvals_total",
            "feature_operator_trusted_autonomous_deliveries_total"
          ],
          "reason": "Autonomous delivery is trusted only when low-risk policy approval later closes successfully."
        }
      },
      "autoApprovalApproved": true
    },
    "architectSpec": {
      "mode": "embedded_in_execution_contract",
      "engineerTier": "Jr",
      "monitoringRunbook": "docs/runbooks/golden-path-autonomous-delivery.md"
    },
    "forgeReadinessNote": "Forge execution readiness remains GP-009; intake-draft DRAFT stage blocks readiness until workflow advances post-approval."
  },
  "github": {
    "branchName": "tsk-017-agent-driven-factory-delivery",
    "commitSha": "7f3a9c2b1e4d6f8a0b5c3d9e2f1a6b7c8d9e0f12",
    "prUrl": "https://github.com/openclaw/engineering-team/pull/17",
    "prNumber": 17
  },
  "phase2": {
    "completedAt": "2026-07-10T16:42:00.424Z",
    "personaRouting": {
      "seededAgents": [
        "engineer-jr",
        "engineer-sr",
        "engineer-principal"
      ],
      "runtimeAgents": {
        "jr-engineer": "jr-engineer",
        "sr-engineer": "sr-engineer",
        "principal": "principal",
        "ux": "ux-designer"
      },
      "assignees": {
        "Jr": "engineer-jr",
        "Sr": "engineer-sr",
        "Principal": "engineer-principal"
      },
      "assignedTier": "Jr",
      "assignedOwner": "engineer-jr",
      "engineerPersonas": {
        "jr": "engineer-jr",
        "sr": "engineer-sr",
        "principal": "engineer-principal"
      }
    },
    "personas": {
      "engineer": "engineer-jr",
      "engineerPersonas": {
        "jr": "engineer-jr",
        "sr": "engineer-sr",
        "principal": "engineer-principal"
      },
      "personaRouting": {
        "seededAgents": [
          "engineer-jr",
          "engineer-sr",
          "engineer-principal"
        ],
        "runtimeAgents": {
          "jr-engineer": "jr-engineer",
          "sr-engineer": "sr-engineer",
          "principal": "principal",
          "ux": "ux-designer"
        },
        "assignees": {
          "Jr": "engineer-jr",
          "Sr": "engineer-sr",
          "Principal": "engineer-principal"
        },
        "assignedTier": "Jr",
        "assignedOwner": "engineer-jr",
        "engineerPersonas": {
          "jr": "engineer-jr",
          "sr": "engineer-sr",
          "principal": "engineer-principal"
        }
      },
      "ux": "ux",
      "delegation": "delegated",
      "forge": "main"
    },
    "api": {
      "seed": {
        "ok": true,
        "skipped": true,
        "reason": "skip_forge_seed"
      },
      "readiness": {
        "status": 200,
        "ready": {
          "ready": true,
          "skipped": true
        }
      },
      "stackHealth": {
        "ok": true,
        "skipped": true,
        "reason": "skip_forge_seed"
      },
      "stackSource": "skip_forge_seed",
      "startJobId": null,
      "runtimeExecutionState": "skipped_forge_seed",
      "pilotAgentsSeed": {
        "ok": true,
        "status": 0
      },
      "personaRouting": {
        "seededAgents": [
          "engineer-jr",
          "engineer-sr",
          "engineer-principal"
        ],
        "runtimeAgents": {
          "jr-engineer": "jr-engineer",
          "sr-engineer": "sr-engineer",
          "principal": "principal",
          "ux": "ux-designer"
        },
        "assignees": {
          "Jr": "engineer-jr",
          "Sr": "engineer-sr",
          "Principal": "engineer-principal"
        },
        "assignedTier": "Jr",
        "assignedOwner": "engineer-jr",
        "engineerPersonas": {
          "jr": "engineer-jr",
          "sr": "engineer-sr",
          "principal": "engineer-principal"
        }
      },
      "implementerAgent": {
        "delegated": true,
        "sessionId": "specialist-delegation-1b19c47e-4a64-4b8d-97c2-190dbb55c0a2",
        "agentId": "jr-engineer",
        "branchName": "tsk-017-agent-driven-factory-delivery",
        "commitSha": "9f2c4b8a6d1e0f3c7b5a9d2e4f6a8c0b1d3e5f7a",
        "prUrl": "https://github.com/openclaw/engineering-team/pull/17"
      },
      "delegationSmoke": {
        "ok": true,
        "skipped": false,
        "sessionId": "specialist-delegation-b299decd-ec85-46c8-80fa-5600746d5bc1"
      },
      "engineerSubmission": {
        "status": 200,
        "ok": true,
        "markerPresentAtSubmission": true
      },
      "implementation": {
        "branchName": "tsk-017-agent-driven-factory-delivery",
        "commitSha": "9f2c4b8a6d1e0f3c7b5a9d2e4f6a8c0b1d3e5f7a",
        "prUrl": "https://github.com/openclaw/engineering-team/pull/17",
        "prNumber": 17
      }
    }
  },
  "phase3": {
    "completedAt": "2026-07-10T16:43:18.971Z",
    "personas": {
      "qa": "qa",
      "qaOutcome": "fail_intentional",
      "engineer": "engineer-jr"
    },
    "api": {
      "qaFail": {
        "status": 201,
        "ok": true,
        "runId": "qa-f4d48da9"
      },
      "qaAgent": {
        "delegated": true,
        "sessionId": "specialist-delegation-28cfa0ce-3261-4383-aab3-6eeb56459ff3",
        "agentId": "qa-engineer",
        "outcome": "fail"
      },
      "forgeRejectJobId": null,
      "executionState": "skipped_forge_seed",
      "workflowState": "skipped_forge_seed"
    }
  },
  "phase4": {
    "completedAt": "2026-07-10T16:44:30.376Z",
    "personas": {
      "engineer": "engineer-sr",
      "qa": "qa",
      "qaOutcome": "pass"
    },
    "api": {
      "readmeFix": {
        "changed": false,
        "path": "/Users/wiinc2/.grok/worktrees/workspace-engineering-team/strategy-review/README.md"
      },
      "engineerSubmission": {
        "status": 200,
        "ok": true
      },
      "forgeResumeJobId": null,
      "runtimeExecutionState": "skipped_forge_seed",
      "qaPass": {
        "status": 201,
        "ok": true
      },
      "fixCommitSha": "7f3a9c2b1e4d6f8a0b5c3d9e2f1a6b7c8d9e0f12"
    }
  },
  "phase5": {
    "completedAt": "2026-07-10T16:44:48.889Z",
    "personas": {
      "sre": "sre",
      "pm": "pm",
      "architect": "architect",
      "qa": "qa",
      "qaVerification": "pass"
    },
    "api": {
      "stageAdvanceForSre": {
        "currentStage": "SRE_MONITORING",
        "transitions": []
      },
      "sreMonitoring": {
        "agentSessionId": "specialist-delegation-9d1cab4b-6b71-41b1-b4ee-fc25366daeb8",
        "agentId": "sre",
        "delegated": true,
        "approved": true
      },
      "stageAdvanceForCloseReview": {
        "currentStage": "PM_CLOSE_REVIEW",
        "transitions": [
          {
            "from": "SRE_MONITORING",
            "to": "PM_CLOSE_REVIEW",
            "status": 202
          }
        ]
      },
      "forgeCompleteJobId": null,
      "executionState": "skipped_forge_seed",
      "workflowState": "skipped_forge_seed",
      "pmCloseReview": {
        "status": 201,
        "ok": true
      },
      "architectCloseReview": {
        "status": 201,
        "ok": true
      }
    }
  }
}
